pyodm/__init__.py
pyodm/exceptions.py
pyodm/core/__init__.py
pyodm/core/data_loader/__init__.py
pyodm/core/data_loader/forest_data_loader.py
pyodm/core/data_loader/json_path_loader.py
pyodm/core/data_loader/xml_path_loader.py
pyodm/core/forest/__init__.py
pyodm/core/forest/reader/__init__.py
pyodm/core/forest/reader/forest_data_reader.py
pyodm/core/json/__init__.py
pyodm/core/json/reader/__init__.py
pyodm/core/json/reader/json_data_reader.py
pyodm/core/json/writer/__init__.py
pyodm/core/json/writer/json_writer.py
pyodm/core/source/__init__.py
pyodm/core/source/abstract_database_source.py
pyodm/core/source/path_source.py
pyodm/core/support/__init__.py
pyodm/core/support/abstact_registration.py
pyodm/core/support/abstract_configuration_reader.py
pyodm/core/support/abstract_data_loader.py
pyodm/core/support/abstract_data_reader.py
pyodm/core/support/abstract_data_source.py
pyodm/core/support/abstract_path_loader.py
pyodm/core/support/abstract_xml_data_reader.py
pyodm/core/xml/__init__.py
pyodm/core/xml/reader/__init__.py
pyodm/core/xml/reader/configuration/__init__.py
pyodm/core/xml/reader/configuration/cdisc_configuration_specification_reader.py
pyodm/core/xml/reader/configuration/cdisc_configuration_xsd_reader.py
pyodm/core/xml/reader/data/__init__.py
pyodm/core/xml/reader/data/xml_v2_data_reader.py
pyodm/core/xml/reader/mapper/__init__.py
pyodm/core/xml/reader/mapper/xml_mapper_reader.py
pyodm/core/xml/writer/__init__.py
pyodm/core/xml/writer/cdisc_xml_writer.py
pyodm/core/xml/writer/write_status.py
pyodm/factory/__init__.py
pyodm/factory/abstract_assemble_factory.py
pyodm/factory/abstract_cdisc_factory.py
pyodm/factory/abstract_cdisc_xml_factory.py
pyodm/factory/abstract_data_object_factory.py
pyodm/factory/abstract_hierarchy_factory.py
pyodm/factory/cdisc_json_factory.py
pyodm/factory/cdisc_listable_factory.py
pyodm/factory/cdisc_registry.py
pyodm/factory/cdisc_xml_spec_factory.py
pyodm/factory/cdsic_xml_v2_factory.py
pyodm/factory/cdsic_xml_xsd_factory.py
pyodm_cn-1.0.4.dist-info/METADATA
pyodm_cn-1.0.4.dist-info/WHEEL
pyodm_cn-1.0.4.dist-info/top_level.txt
pyodm_cn-1.0.4.dist-info/RECORD
