Metadata-Version: 2.1
Name: pyodm-cn
Version: 1.0.4
Summary: odm support tool
Home-page: https://github.com/thcpc/pyodm
Author: thcpc
Author-email: redcpc@163.com
License: UNKNOWN
Project-URL: Bug Tracker, https://github.com/thcpc/pyodm
Platform: UNKNOWN
Classifier: Programming Language :: Python :: 3
Classifier: License :: OSI Approved :: MIT License
Classifier: Operating System :: OS Independent
Requires-Python: >=3.9
Requires-Dist: lxml
Requires-Dist: pytest
Requires-Dist: cjen
